docs/source/conf.py
paspailleur/__init__.py
paspailleur/datasets.py
paspailleur/algorithms/__init__.py
paspailleur/algorithms/base_functions.py
paspailleur/algorithms/mine_equivalence_classes.py
paspailleur/algorithms/mine_implication_bases.py
paspailleur/algorithms/mine_subgroups.py
paspailleur/pattern_structures/__init__.py
paspailleur/pattern_structures/built_in_patterns.py
paspailleur/pattern_structures/pattern.py
paspailleur/pattern_structures/pattern_structure.py
paspailleur-0.1.0.dist-info/licenses/LICENSE
tests/test_algorithms/test_base_functions.py
tests/test_algorithms/test_mine_equivalence_classes.py
tests/test_pattern_structures/test_built_in_patterns.py
tests/test_pattern_structures/test_pattern.py
tests/test_pattern_structures/test_pattern_structure.py
paspailleur-0.1.0.dist-info/METADATA
paspailleur-0.1.0.dist-info/WHEEL
paspailleur-0.1.0.dist-info/top_level.txt
paspailleur-0.1.0.dist-info/RECORD
