Metadata-Version: 2.4
Name: paspailleur
Version: 0.1.0
Summary: Pattern Structures miner in Python. An add-on for Caspailleur package. Part of SmartFCA project
Author: Egor Dudyrev
License:                     GNU GENERAL PUBLIC LICENSE
Project-URL: Homepage, https://github.com/EgorDudyrev/paspailleur
Keywords: python,fca,itemset-mining
Classifier: Programming Language :: Python :: 3
Classifier: Programming Language :: Python :: 3.8
Classifier: License :: OSI Approved :: GNU General Public License v3 (GPLv3)
Classifier: Operating System :: OS Independent
Requires-Python: >=3.8
License-File: LICENSE
Requires-Dist: caspailleur>=0.2.1
Requires-Dist: bitarray>=3
Requires-Dist: tqdm
Requires-Dist: deprecation
Requires-Dist: frozendict
Dynamic: license-file
